gf180mcu_pdk/__init__.py
gf180mcu_pdk-0.0.0.dist-info/LICENSE
gf180mcu_pdk-0.0.0.dist-info/METADATA
gf180mcu_pdk-0.0.0.dist-info/WHEEL
gf180mcu_pdk-0.0.0.dist-info/top_level.txt
gf180mcu_pdk-0.0.0.dist-info/RECORD
